sway/__init__.py
sway/__main__.py
sway/commands/__init__.py
sway/commands/branch.py
sway/commands/build.py
sway/commands/config.py
sway/main.py
sway/utils/__init__.py
sway/utils/config.py
sway/utils/yaml.py
sway-0.1.4.dist-info/METADATA
sway-0.1.4.dist-info/WHEEL
sway-0.1.4.dist-info/entry_points.txt
sway-0.1.4.dist-info/RECORD
