Metadata-Version: 2.1
Name: sway
Version: 0.1.4
Summary: managing micro-repos for monorepos
License: MIT
Author: Saurabh Chopra
Author-email: sc@saurabhchopra.co.uk
Requires-Python: >=3.8,<4.0
Classifier: License :: OSI Approved :: MIT License
Classifier: Programming Language :: Python :: 3
Classifier: Programming Language :: Python :: 3.8
Classifier: Programming Language :: Python :: 3.9
Classifier: Programming Language :: Python :: 3.10
Classifier: Programming Language :: Python :: 3.11
Requires-Dist: pyyaml (>=6.0,<7.0)
